README.rst
setup.py
KNN_TextClassifier.egg-info/PKG-INFO
KNN_TextClassifier.egg-info/SOURCES.txt
KNN_TextClassifier.egg-info/dependency_links.txt
KNN_TextClassifier.egg-info/requires.txt
KNN_TextClassifier.egg-info/top_level.txt
src/KNN.py