Metadata-Version: 1.1
Name: KNN-TextClassifier
Version: 0.0.0
Summary: KNN_TextClassifier
Home-page: https://github.com/ArnoldGaius/KNN_TextClassifier
Author: Arnold_Gaius
Author-email: jiangcmd@qq.com
License: BSD
Platform: UNKNOWN
Classifier: Programming Language :: Python
Classifier: Programming Language :: Python :: 2
Classifier: Programming Language :: Python :: 2.7
